<item><country>Spain</country><league>Spain LaLiga</league><season>2016/2017</season><stage>38</stage><matchId>2300882</matchId><date>2017-05-21 19:00</date><homeTeamId><value>8634</value></homeTeamId><awayTeamId><value>8372</value></awayTeamId><homeTeamFullName><value>Barcelona</value></homeTeamFullName><awayTeamFullName><value>Eibar</value></awayTeamFullName><homeTeamAcronym><value>EIB</value></homeTeamAcronym><awayTeamAcronym><value>BAR</value></awayTeamAcronym><homeTeamGoal>None</homeTeamGoal><awayTeamGoal>None</awayTeamGoal><homePlayers><value>Marc-Andre ter Stegen</value><value>Sergi Roberto</value><value>Samuel Umtiti</value><value>Jordi Alba</value><value>Marlon</value><value>Ivan Rakitic</value><value>Sergio Busquets</value><value>Andres Iniesta</value><value>Lionel Messi</value><value>Luis Suarez</value><value>Neymar</value></homePlayers><awayPlayers><value>Yoel Rodriguez</value><value>Ander Capa</value><value>Florian Lejeune</value><value>Anaitz Arbilla</value><value>David Junca</value><value>Ruben Jimenez Pena</value><value>Gonzalo Escalante</value><value>Dani Garcia</value><value>Takashi Inui</value><value>Sergi Enrich</value><value>Kike</value></awayPlayers><homePlayersId><value>184554</value><value>150739</value><value>212472</value><value>210117</value><value>540113</value><value>25773</value><value>154257</value><value>30955</value><value>40636</value><value>30981</value><value>19533</value></homePlayersId><awayPlayersId><value>192064</value><value>449492</value><value>213814</value><value>184521</value><value>246218</value><value>434404</value><value>97762</value><value>364239</value><value>433311</value><value>193224</value><value>183353</value></awayPlayersId><homePlayersX><value>1</value><value>2</value><value>6</value><value>8</value><value>4</value><value>3</value><value>5</value><value>7</value><value>3</value><value>5</value><value>7</value></homePlayersX><awayPlayersX><value>1</value><value>2</value><value>4</value><value>6</value><value>8</value><value>2</value><value>4</value><value>6</value><value>8</value><value>4</value><value>6</value></awayPlayersX><homePlayersY><value>1</value><value>3</value><value>3</value><value>3</value><value>3</value><value>7</value><value>7</value><value>7</value><value>10</value><value>10</value><value>10</value></homePlayersY><awayPlayersY><value>1</value><value>3</value><value>3</value><value>3</value><value>3</value><value>7</value><value>7</value><value>7</value><value>7</value><value>10</value><value>10</value></awayPlayersY><goal><value><comment>n</comment><stats><goals>1</goals><shoton>1</shoton></stats><event_incident_typefk>393</event_incident_typefk><coordinates><value>30</value><value>65</value></coordinates><elapsed>7</elapsed><player2>449492</player2><subtype>shot</subtype><player1>97762</player1><sortorder>2</sortorder><team>8372</team><id>6743708</id><n>51</n><type>goal</type><goal_type>n</goal_type></value><value><comment>n</comment><stats><goals>1</goals><shoton>1</shoton></stats><event_incident_typefk>393</event_incident_typefk><coordinates><value>32</value><value>62</value></coordinates><elapsed>61</elapsed><player2>193224</player2><subtype>shot</subtype><player1>97762</player1><sortorder>3</sortorder><team>8372</team><id>6744081</id><n>325</n><type>goal</type><goal_type>n</goal_type></value><value><comment>o</comment><stats><owngoals>1</owngoals></stats><event_incident_typefk>115</event_incident_typefk><coordinates><value>25</value><value>2</value></coordinates><elapsed>63</elapsed><player1>246218</player1><sortorder>2</sortorder><team>8372</team><id>6744096</id><n>346</n><type>goal</type><goal_type>o</goal_type></value><value><comment>npm</comment><stats><shoton>1</shoton></stats><event_incident_typefk>159</event_incident_typefk><coordinates><value>23</value><value>8</value></coordinates><elapsed>70</elapsed><subtype>saved</subtype><player1>30981</player1><sortorder>1</sortorder><team>8634</team><id>6744150</id><n>370</n><type>goal</type><goal_type>npm</goal_type></value><value><comment>n</comment><stats><goals>1</goals><shoton>1</shoton></stats><event_incident_typefk>721</event_incident_typefk><coordinates><value>25</value><value>2</value></coordinates><elapsed>73</elapsed><player2>241825</player2><subtype>tap_in</subtype><player1>40636</player1><sortorder>4</sortorder><team>8634</team><id>6744178</id><n>430</n><type>goal</type><goal_type>n</goal_type></value><value><comment>p</comment><stats><goals>1</goals><shoton>1</shoton></stats><event_incident_typefk>20</event_incident_typefk><coordinates><value>23</value><value>8</value></coordinates><elapsed>75</elapsed><player1>30981</player1><sortorder>2</sortorder><team>8634</team><id>6744186</id><n>409</n><type>goal</type><goal_type>p</goal_type></value><value><comment>n</comment><stats><goals>1</goals><shoton>1</shoton></stats><elapsed_plus>2</elapsed_plus><event_incident_typefk>80</event_incident_typefk><coordinates><value>25</value><value>9</value></coordinates><elapsed>90</elapsed><subtype>shot</subtype><player1>30981</player1><sortorder>9</sortorder><team>8634</team><id>6744301</id><n>512</n><type>goal</type><goal_type>n</goal_type></value></goal><shoton><value><stats><shoton>1</shoton></stats><event_incident_typefk>135</event_incident_typefk><coordinates><value>35</value><value>7</value></coordinates><elapsed>18</elapsed><subtype>shot</subtype><player1>30981</player1><sortorder>2</sortorder><team>8634</team><n>111</n><type>shoton</type><id>6743764</id></value><value><stats><shoton>1</shoton></stats><event_incident_typefk>135</event_incident_typefk><coordinates><value>28</value><value>8</value></coordinates><elapsed>33</elapsed><subtype>shot</subtype><player1>25773</player1><sortorder>2</sortorder><team>8634</team><n>177</n><type>shoton</type><id>6743832</id></value><value><stats><shoton>1</shoton></stats><event_incident_typefk>552</event_incident_typefk><coordinates><value>23</value><value>12</value></coordinates><elapsed>36</elapsed><subtype>big chance shot</subtype><player1>40636</player1><sortorder>1</sortorder><team>8634</team><n>193</n><type>shoton</type><id>6743843</id></value><value><stats><shoton>1</shoton></stats><event_incident_typefk>153</event_incident_typefk><coordinates><value>25</value><value>60</value></coordinates><elapsed>45</elapsed><subtype>shot</subtype><player1>97762</player1><sortorder>1</sortorder><team>8372</team><n>236</n><type>shoton</type><id>6743893</id></value><value><stats><shoton>1</shoton></stats><event_incident_typefk>147</event_incident_typefk><coordinates><value>33</value><value>68</value></coordinates><elapsed>47</elapsed><subtype>shot</subtype><player1>97762</player1><sortorder>1</sortorder><team>8372</team><n>258</n><type>shoton</type><id>6743956</id></value><value><stats><shoton>1</shoton></stats><event_incident_typefk>153</event_incident_typefk><coordinates><value>15</value><value>10</value></coordinates><elapsed>50</elapsed><subtype>shot</subtype><player1>30955</player1><sortorder>1</sortorder><team>8634</team><n>275</n><type>shoton</type><id>6743988</id></value><value><stats><shoton>1</shoton></stats><event_incident_typefk>147</event_incident_typefk><coordinates><value>21</value><value>10</value></coordinates><elapsed>52</elapsed><subtype>shot</subtype><player1>30955</player1><sortorder>2</sortorder><team>8634</team><n>282</n><type>shoton</type><id>6744007</id></value><value><stats><blocked>1</blocked></stats><event_incident_typefk>61</event_incident_typefk><coordinates><value>28</value><value>10</value></coordinates><elapsed>65</elapsed><subtype>blocked_shot</subtype><player1>30981</player1><sortorder>1</sortorder><team>8634</team><n>349</n><type>shoton</type><id>6744108</id></value><value><stats><shoton>1</shoton></stats><event_incident_typefk>136</event_incident_typefk><coordinates><value>22</value><value>6</value></coordinates><elapsed>78</elapsed><subtype>header</subtype><player1>241825</player1><sortorder>0</sortorder><team>8634</team><n>423</n><type>shoton</type><id>6744206</id></value><value><stats><shoton>1</shoton></stats><elapsed_plus>2</elapsed_plus><event_incident_typefk>553</event_incident_typefk><coordinates><value>26</value><value>8</value></coordinates><elapsed>90</elapsed><subtype>big chance shot</subtype><player1>40636</player1><sortorder>7</sortorder><team>8634</team><n>485</n><type>shoton</type><id>6744300</id></value></shoton><shotoff><value><stats><shotoff>1</shotoff></stats><event_incident_typefk>587</event_incident_typefk><coordinates><value>23</value><value>10</value></coordinates><elapsed>9</elapsed><subtype>big chance shot</subtype><player1>40636</player1><sortorder>1</sortorder><team>8634</team><n>62</n><type>shotoff</type><id>6743715</id></value><value><stats><shotoff>1</shotoff></stats><event_incident_typefk>46</event_incident_typefk><coordinates><value>25</value><value>12</value></coordinates><elapsed>13</elapsed><subtype>shot</subtype><player1>40636</player1><sortorder>1</sortorder><team>8634</team><n>80</n><type>shotoff</type><id>6743734</id></value><value><stats><shotoff>1</shotoff></stats><event_incident_typefk>47</event_incident_typefk><coordinates><value>32</value><value>4</value></coordinates><elapsed>38</elapsed><subtype>header</subtype><player1>30981</player1><sortorder>1</sortorder><team>8634</team><n>203</n><type>shotoff</type><id>6743854</id></value><value><stats><shotoff>1</shotoff></stats><event_incident_typefk>587</event_incident_typefk><coordinates><value>17</value><value>63</value></coordinates><elapsed>45</elapsed><subtype>big chance shot</subtype><player1>364239</player1><sortorder>2</sortorder><team>8372</team><n>237</n><type>shotoff</type><id>6743894</id></value><value><stats><shotoff>1</shotoff></stats><event_incident_typefk>587</event_incident_typefk><coordinates><value>21</value><value>6</value></coordinates><elapsed>56</elapsed><subtype>big chance shot</subtype><player1>30981</player1><sortorder>2</sortorder><team>8634</team><n>309</n><type>shotoff</type><id>6744046</id></value><value><stats><shotoff>1</shotoff></stats><event_incident_typefk>113</event_incident_typefk><coordinates><value>14</value><value>8</value></coordinates><elapsed>63</elapsed><subtype>post</subtype><player1>19533</player1><sortorder>1</sortorder><team>8634</team><n>337</n><type>shotoff</type><id>6744093</id></value><value><stats><shotoff>1</shotoff></stats><event_incident_typefk>587</event_incident_typefk><coordinates><value>20</value><value>8</value></coordinates><elapsed>67</elapsed><subtype>big chance shot</subtype><player1>19533</player1><sortorder>2</sortorder><team>8634</team><n>359</n><type>shotoff</type><id>6744123</id></value><value><stats><shotoff>1</shotoff></stats><elapsed_plus>3</elapsed_plus><event_incident_typefk>47</event_incident_typefk><coordinates><value>26</value><value>63</value></coordinates><elapsed>90</elapsed><subtype>header</subtype><player1>183353</player1><sortorder>11</sortorder><team>8372</team><n>499</n><type>shotoff</type><id>6744307</id></value></shotoff><foulcommit><value><stats><foulscommitted>1</foulscommitted></stats><event_incident_typefk>730</event_incident_typefk><coordinates><value>22</value><value>50</value></coordinates><elapsed>2</elapsed><player2>210117</player2><subtype>trip</subtype><player1>193224</player1><sortorder>0</sortorder><team>8372</team><n>8</n><type>foulcommit</type><id>6743675</id></value><value><stats><foulscommitted>1</foulscommitted></stats><event_incident_typefk>37</event_incident_typefk><coordinates><value>3</value><value>32</value></coordinates><elapsed>17</elapsed><player2>19533</player2><player1>364239</player1><sortorder>0</sortorder><team>8372</team><n>98</n><type>foulcommit</type><id>6743755</id></value><value><stats><foulscommitted>1</foulscommitted></stats><event_incident_typefk>730</event_incident_typefk><coordinates><value>29</value><value>44</value></coordinates><elapsed>18</elapsed><player2>25773</player2><subtype>trip</subtype><player1>183353</player1><sortorder>3</sortorder><team>8372</team><n>114</n><type>foulcommit</type><id>6743766</id></value><value><stats><foulscommitted>1</foulscommitted></stats><event_incident_typefk>5</event_incident_typefk><coordinates><value>20</value><value>27</value></coordinates><elapsed>19</elapsed><player2>154257</player2><subtype>serious_foul</subtype><player1>434404</player1><sortorder>2</sortorder><team>8372</team><n>120</n><type>foulcommit</type><id>6743771</id></value><value><stats><foulscommitted>1</foulscommitted></stats><event_incident_typefk>19</event_incident_typefk><coordinates><value>29</value><value>32</value></coordinates><elapsed>24</elapsed><player2>25773</player2><subtype>from_behind</subtype><player1>433311</player1><sortorder>0</sortorder><team>8372</team><n>141</n><type>foulcommit</type><id>6743792</id></value><value><stats><foulscommitted>1</foulscommitted></stats><event_incident_typefk>730</event_incident_typefk><coordinates><value>5</value><value>40</value></coordinates><elapsed>30</elapsed><player2>30955</player2><subtype>trip</subtype><player1>449492</player1><sortorder>1</sortorder><team>8372</team><n>159</n><type>foulcommit</type><id>6743822</id></value><value><stats><foulscommitted>1</foulscommitted></stats><event_incident_typefk>43</event_incident_typefk><coordinates><value>19</value><value>27</value></coordinates><elapsed>34</elapsed><player1>434404</player1><sortorder>1</sortorder><team>8372</team><n>183</n><type>foulcommit</type><id>6743837</id></value><value><stats><foulscommitted>1</foulscommitted></stats><event_incident_typefk>37</event_incident_typefk><coordinates><value>37</value><value>21</value></coordinates><elapsed>37</elapsed><player2>154257</player2><player1>433311</player1><sortorder>2</sortorder><team>8372</team><n>200</n><type>foulcommit</type><id>6743850</id></value><value><stats><foulscommitted>1</foulscommitted></stats><event_incident_typefk>647</event_incident_typefk><coordinates><value>23</value><value>41</value></coordinates><elapsed>40</elapsed><player2>183353</player2><subtype>dangerous_play</subtype><player1>154257</player1><sortorder>1</sortorder><team>8634</team><n>212</n><type>foulcommit</type><id>6743866</id></value><value><stats><foulscommitted>1</foulscommitted></stats><event_incident_typefk>37</event_incident_typefk><coordinates><value>22</value><value>52</value></coordinates><elapsed>43</elapsed><player2>210117</player2><player1>434404</player1><sortorder>0</sortorder><team>8372</team><n>223</n><type>foulcommit</type><id>6743885</id></value><value><stats><foulscommitted>1</foulscommitted></stats><event_incident_typefk>37</event_incident_typefk><coordinates><value>12</value><value>2</value></coordinates><elapsed>53</elapsed><player2>213814</player2><player1>40636</player1><sortorder>2</sortorder><team>8634</team><n>291</n><type>foulcommit</type><id>6744012</id></value><value><stats><foulscommitted>1</foulscommitted></stats><event_incident_typefk>43</event_incident_typefk><coordinates><value>7</value><value>41</value></coordinates><elapsed>54</elapsed><player1>434404</player1><sortorder>0</sortorder><team>8372</team><n>294</n><type>foulcommit</type><id>6744018</id></value><value><stats><foulscommitted>1</foulscommitted></stats><event_incident_typefk>118</event_incident_typefk><coordinates><value>17</value><value>9</value></coordinates><elapsed>70</elapsed><player2>150739</player2><subtype>penalty</subtype><player1>75192</player1><sortorder>0</sortorder><team>8372</team><n>367</n><type>foulcommit</type><id>6744145</id></value><value><stats><foulscommitted>1</foulscommitted></stats><event_incident_typefk>38</event_incident_typefk><coordinates><value>13</value><value>4</value></coordinates><elapsed>74</elapsed><player2>19533</player2><subtype>penalty</subtype><player1>449492</player1><sortorder>0</sortorder><team>8372</team><n>504</n><type>foulcommit</type><id>6744181</id></value><value><stats><foulscommitted>1</foulscommitted></stats><event_incident_typefk>730</event_incident_typefk><coordinates><value>17</value><value>23</value></coordinates><elapsed>87</elapsed><player2>19533</player2><subtype>trip</subtype><player1>213814</player1><sortorder>0</sortorder><team>8372</team><n>461</n><type>foulcommit</type><id>6744268</id></value><value><stats><foulscommitted>1</foulscommitted></stats><event_incident_typefk>37</event_incident_typefk><coordinates><value>5</value><value>31</value></coordinates><elapsed>89</elapsed><player2>183353</player2><player1>19533</player1><sortorder>0</sortorder><team>8634</team><n>466</n><type>foulcommit</type><id>6744276</id></value></foulcommit><card><value><comment>y</comment><stats><ycards>1</ycards></stats><event_incident_typefk>70</event_incident_typefk><elapsed>19</elapsed><card_type>y</card_type><player1>434404</player1><sortorder>3</sortorder><team>8372</team><n>118</n><type>card</type><id>6743772</id></value><value><comment>y</comment><stats><ycards>1</ycards></stats><event_incident_typefk>70</event_incident_typefk><elapsed>30</elapsed><card_type>y</card_type><player1>449492</player1><sortorder>2</sortorder><team>8372</team><n>161</n><type>card</type><id>6743823</id></value><value><comment>y</comment><stats><ycards>1</ycards></stats><event_incident_typefk>70</event_incident_typefk><elapsed>41</elapsed><card_type>y</card_type><player1>154257</player1><sortorder>0</sortorder><team>8634</team><n>248</n><type>card</type><id>6743943</id></value><value><comment>y</comment><stats><ycards>1</ycards></stats><event_incident_typefk>25</event_incident_typefk><elapsed>54</elapsed><card_type>y</card_type><subtype>stall_time</subtype><player1>364239</player1><sortorder>1</sortorder><team>8372</team><n>295</n><type>card</type><id>6744021</id></value><value><comment>y2</comment><stats><rcards>1</rcards></stats><event_incident_typefk>26</event_incident_typefk><elapsed>74</elapsed><card_type>y2</card_type><player1>449492</player1><sortorder>1</sortorder><team>8372</team><n>505</n><type>card</type><id>6744182</id></value></card><cross><value><stats><crosses>1</crosses></stats><event_incident_typefk>7</event_incident_typefk><coordinates><value>34</value><value>48</value></coordinates><elapsed>4</elapsed><subtype>cross</subtype><player1>433311</player1><sortorder>1</sortorder><team>8372</team><n>18</n><type>cross</type><id>6743688</id></value><value><stats><crosses>1</crosses></stats><event_incident_typefk>7</event_incident_typefk><coordinates><value>41</value><value>63</value></coordinates><elapsed>6</elapsed><subtype>cross</subtype><player1>97762</player1><sortorder>0</sortorder><team>8372</team><n>30</n><type>cross</type><id>6743697</id></value><value><stats><crosses>1</crosses></stats><event_incident_typefk>7</event_incident_typefk><coordinates><value>5</value><value>56</value></coordinates><elapsed>7</elapsed><subtype>cross</subtype><player1>449492</player1><sortorder>1</sortorder><team>8372</team><n>41</n><type>cross</type><id>6743707</id></value><value><stats><crosses>1</crosses></stats><event_incident_typefk>770</event_incident_typefk><coordinates><value>8</value><value>67</value></coordinates><elapsed>11</elapsed><subtype>cross</subtype><player1>364239</player1><sortorder>0</sortorder><team>8372</team><n>71</n><type>cross</type><id>6743725</id></value><value><stats><crosses>1</crosses></stats><event_incident_typefk>7</event_incident_typefk><coordinates><value>37</value><value>58</value></coordinates><elapsed>12</elapsed><subtype>cross</subtype><player1>97762</player1><sortorder>0</sortorder><team>8372</team><n>77</n><type>cross</type><id>6743728</id></value><value><stats><crosses>1</crosses></stats><event_incident_typefk>770</event_incident_typefk><coordinates><value>42</value><value>61</value></coordinates><elapsed>30</elapsed><subtype>cross</subtype><player1>364239</player1><sortorder>0</sortorder><team>8372</team><n>158</n><type>cross</type><id>6743819</id></value><value><stats><crosses>1</crosses></stats><event_incident_typefk>7</event_incident_typefk><coordinates><value>19</value><value>19</value></coordinates><elapsed>38</elapsed><subtype>cross</subtype><player1>30955</player1><sortorder>0</sortorder><team>8634</team><n>202</n><type>cross</type><id>6743853</id></value><value><stats><crosses>1</crosses></stats><event_incident_typefk>770</event_incident_typefk><coordinates><value>42</value><value>66</value></coordinates><elapsed>42</elapsed><subtype>cross</subtype><player1>184521</player1><sortorder>0</sortorder><team>8372</team><n>219</n><type>cross</type><id>6743879</id></value><value><stats><crosses>1</crosses></stats><event_incident_typefk>770</event_incident_typefk><coordinates><value>7</value><value>6</value></coordinates><elapsed>44</elapsed><subtype>cross</subtype><player1>19533</player1><sortorder>0</sortorder><team>8634</team><n>229</n><type>cross</type><id>6743887</id></value><value><stats><crosses>1</crosses></stats><event_incident_typefk>7</event_incident_typefk><coordinates><value>37</value><value>54</value></coordinates><elapsed>45</elapsed><subtype>cross</subtype><player1>246218</player1><sortorder>0</sortorder><team>8372</team><n>234</n><type>cross</type><id>6743892</id></value><value><stats><crosses>1</crosses></stats><event_incident_typefk>770</event_incident_typefk><coordinates><value>7</value><value>4</value></coordinates><elapsed>49</elapsed><subtype>cross</subtype><player1>19533</player1><sortorder>0</sortorder><team>8634</team><n>269</n><type>cross</type><id>6743976</id></value><value><stats><crosses>1</crosses></stats><event_incident_typefk>7</event_incident_typefk><coordinates><value>6</value><value>8</value></coordinates><elapsed>60</elapsed><subtype>cross</subtype><player1>40636</player1><sortorder>0</sortorder><team>8634</team><n>314</n><type>cross</type><id>6744070</id></value><value><stats><crosses>1</crosses></stats><event_incident_typefk>7</event_incident_typefk><coordinates><value>6</value><value>9</value></coordinates><elapsed>83</elapsed><subtype>cross</subtype><player1>19533</player1><sortorder>1</sortorder><team>8634</team><n>444</n><type>cross</type><id>6744240</id></value><value><stats><crosses>1</crosses></stats><event_incident_typefk>7</event_incident_typefk><coordinates><value>6</value><value>58</value></coordinates><elapsed>84</elapsed><subtype>cross</subtype><player1>75192</player1><sortorder>0</sortorder><team>8372</team><n>507</n><type>cross</type><id>6744249</id></value><value><stats><crosses>1</crosses></stats><event_incident_typefk>774</event_incident_typefk><coordinates><value>17</value><value>23</value></coordinates><elapsed>88</elapsed><subtype>cross</subtype><player1>30981</player1><sortorder>0</sortorder><team>8634</team><n>462</n><type>cross</type><id>6744271</id></value><value><stats><crosses>1</crosses></stats><event_incident_typefk>7</event_incident_typefk><coordinates><value>40</value><value>58</value></coordinates><elapsed>89</elapsed><subtype>cross</subtype><player1>246218</player1><sortorder>1</sortorder><team>8372</team><n>468</n><type>cross</type><id>6744280</id></value><value><stats><crosses>1</crosses></stats><event_incident_typefk>7</event_incident_typefk><coordinates><value>6</value><value>54</value></coordinates><elapsed>90</elapsed><subtype>cross</subtype><player1>213814</player1><sortorder>0</sortorder><team>8372</team><n>471</n><type>cross</type><id>6744283</id></value><value><stats><crosses>1</crosses></stats><elapsed_plus>3</elapsed_plus><event_incident_typefk>7</event_incident_typefk><coordinates><value>5</value><value>54</value></coordinates><elapsed>90</elapsed><subtype>cross</subtype><player1>75192</player1><sortorder>10</sortorder><team>8372</team><n>495</n><type>cross</type><id>6744306</id></value></cross><corner><value><stats><corners>1</corners></stats><event_incident_typefk>867</event_incident_typefk><coordinates><value>1</value><value>1</value></coordinates><elapsed>5</elapsed><subtype>cross_left</subtype><player1>19533</player1><sortorder>4</sortorder><team>8634</team><n>24</n><type>corner</type><id>6743693</id></value><value><stats><corners>1</corners></stats><event_incident_typefk>869</event_incident_typefk><coordinates><value>1</value><value>69</value></coordinates><elapsed>11</elapsed><subtype>cross_right</subtype><player1>213814</player1><sortorder>1</sortorder><team>8372</team><n>75</n><type>corner</type><id>6743727</id></value><value><stats><corners>1</corners></stats><event_incident_typefk>867</event_incident_typefk><coordinates><value>1</value><value>1</value></coordinates><elapsed>15</elapsed><subtype>cross_left</subtype><player1>19533</player1><sortorder>2</sortorder><team>8634</team><n>90</n><type>corner</type><id>6743748</id></value><value><stats><corners>1</corners></stats><event_incident_typefk>871</event_incident_typefk><coordinates><value>1</value><value>1</value></coordinates><elapsed>18</elapsed><subtype>short_left</subtype><player1>19533</player1><sortorder>0</sortorder><team>8634</team><n>108</n><type>corner</type><id>6743761</id></value><value><stats><corners>1</corners></stats><event_incident_typefk>867</event_incident_typefk><coordinates><value>1</value><value>1</value></coordinates><elapsed>23</elapsed><subtype>cross_left</subtype><player1>19533</player1><sortorder>2</sortorder><team>8634</team><n>134</n><type>corner</type><id>6743787</id></value><value><stats><corners>1</corners></stats><event_incident_typefk>869</event_incident_typefk><coordinates><value>45</value><value>1</value></coordinates><elapsed>28</elapsed><subtype>cross_right</subtype><player1>19533</player1><sortorder>0</sortorder><team>8634</team><n>150</n><type>corner</type><id>6743808</id></value><value><stats><corners>1</corners></stats><event_incident_typefk>867</event_incident_typefk><coordinates><value>1</value><value>1</value></coordinates><elapsed>37</elapsed><subtype>cross_left</subtype><player1>19533</player1><sortorder>0</sortorder><team>8634</team><n>196</n><type>corner</type><id>6743846</id></value><value><stats><corners>1</corners></stats><event_incident_typefk>867</event_incident_typefk><coordinates><value>45</value><value>69</value></coordinates><elapsed>41</elapsed><subtype>cross_left</subtype><player1>246218</player1><sortorder>2</sortorder><team>8372</team><n>511</n><type>corner</type><id>6743875</id></value><value><stats><corners>1</corners></stats><event_incident_typefk>867</event_incident_typefk><coordinates><value>45</value><value>69</value></coordinates><elapsed>42</elapsed><subtype>cross_left</subtype><player1>246218</player1><sortorder>1</sortorder><team>8372</team><n>220</n><type>corner</type><id>6743882</id></value><value><stats><corners>1</corners></stats><event_incident_typefk>867</event_incident_typefk><coordinates><value>45</value><value>69</value></coordinates><elapsed>47</elapsed><subtype>cross_left</subtype><player1>246218</player1><sortorder>2</sortorder><team>8372</team><n>259</n><type>corner</type><id>6743962</id></value><value><stats><corners>1</corners></stats><event_incident_typefk>869</event_incident_typefk><coordinates><value>45</value><value>1</value></coordinates><elapsed>53</elapsed><subtype>cross_right</subtype><player1>25773</player1><sortorder>0</sortorder><team>8634</team><n>286</n><type>corner</type><id>6744010</id></value><value><stats><corners>1</corners></stats><event_incident_typefk>867</event_incident_typefk><coordinates><value>1</value><value>1</value></coordinates><elapsed>65</elapsed><subtype>cross_left</subtype><player1>19533</player1><sortorder>0</sortorder><team>8634</team><n>348</n><type>corner</type><id>6744106</id></value><value><stats><corners>1</corners></stats><event_incident_typefk>867</event_incident_typefk><coordinates><value>1</value><value>1</value></coordinates><elapsed>71</elapsed><subtype>cross_left</subtype><player1>19533</player1><sortorder>0</sortorder><team>8634</team><n>371</n><type>corner</type><id>6744152</id></value><value><stats><corners>1</corners></stats><event_incident_typefk>867</event_incident_typefk><coordinates><value>1</value><value>1</value></coordinates><elapsed>73</elapsed><subtype>cross_left</subtype><player1>19533</player1><sortorder>2</sortorder><team>8634</team><n>389</n><type>corner</type><id>6744175</id></value></corner><possession><value><comment>64</comment><stats><homepos>64</homepos><awaypos>36</awaypos></stats><event_incident_typefk>352</event_incident_typefk><elapsed>5</elapsed><subtype>possession</subtype><sortorder>3</sortorder><awaypos>36</awaypos><homepos>64</homepos><n>23</n><type>special</type><id>6743692</id></value><value><comment>52</comment><stats><homepos>52</homepos><awaypos>48</awaypos></stats><event_incident_typefk>352</event_incident_typefk><elapsed>10</elapsed><subtype>possession</subtype><sortorder>0</sortorder><awaypos>48</awaypos><homepos>52</homepos><n>67</n><type>special</type><id>6743719</id></value><value><comment>60</comment><stats><homepos>60</homepos><awaypos>40</awaypos></stats><event_incident_typefk>352</event_incident_typefk><elapsed>15</elapsed><subtype>possession</subtype><sortorder>1</sortorder><awaypos>40</awaypos><homepos>60</homepos><n>89</n><type>special</type><id>6743747</id></value><value><comment>67</comment><stats><homepos>67</homepos><awaypos>33</awaypos></stats><event_incident_typefk>352</event_incident_typefk><elapsed>21</elapsed><subtype>possession</subtype><sortorder>2</sortorder><awaypos>33</awaypos><homepos>67</homepos><n>128</n><type>special</type><id>6743781</id></value><value><comment>70</comment><stats><homepos>70</homepos><awaypos>30</awaypos></stats><event_incident_typefk>352</event_incident_typefk><elapsed>25</elapsed><subtype>possession</subtype><sortorder>0</sortorder><awaypos>30</awaypos><homepos>70</homepos><n>143</n><type>special</type><id>6743800</id></value><value><comment>69</comment><stats><homepos>69</homepos><awaypos>31</awaypos></stats><event_incident_typefk>352</event_incident_typefk><elapsed>31</elapsed><subtype>possession</subtype><sortorder>0</sortorder><awaypos>31</awaypos><homepos>69</homepos><n>162</n><type>special</type><id>6743824</id></value><value><comment>70</comment><stats><homepos>70</homepos><awaypos>30</awaypos></stats><event_incident_typefk>352</event_incident_typefk><elapsed>35</elapsed><subtype>possession</subtype><sortorder>1</sortorder><awaypos>30</awaypos><homepos>70</homepos><n>186</n><type>special</type><id>6743840</id></value><value><comment>69</comment><stats><homepos>69</homepos><awaypos>31</awaypos></stats><event_incident_typefk>352</event_incident_typefk><elapsed>40</elapsed><subtype>possession</subtype><sortorder>0</sortorder><awaypos>31</awaypos><homepos>69</homepos><n>209</n><type>special</type><id>6743865</id></value><value><comment>67</comment><stats><homepos>67</homepos><awaypos>33</awaypos></stats><event_incident_typefk>352</event_incident_typefk><elapsed>45</elapsed><subtype>possession</subtype><sortorder>5</sortorder><awaypos>33</awaypos><homepos>67</homepos><n>246</n><type>special</type><id>6743939</id></value><value><comment>68</comment><stats><homepos>68</homepos><awaypos>32</awaypos></stats><event_incident_typefk>352</event_incident_typefk><elapsed>51</elapsed><subtype>possession</subtype><sortorder>0</sortorder><awaypos>32</awaypos><homepos>68</homepos><n>277</n><type>special</type><id>6743992</id></value><value><comment>69</comment><stats><homepos>69</homepos><awaypos>31</awaypos></stats><event_incident_typefk>352</event_incident_typefk><elapsed>55</elapsed><subtype>possession</subtype><sortorder>1</sortorder><awaypos>31</awaypos><homepos>69</homepos><n>302</n><type>special</type><id>6744033</id></value><value><comment>69</comment><stats><homepos>69</homepos><awaypos>31</awaypos></stats><event_incident_typefk>352</event_incident_typefk><elapsed>61</elapsed><subtype>possession</subtype><sortorder>1</sortorder><awaypos>31</awaypos><homepos>69</homepos><n>318</n><type>special</type><id>6744078</id></value><value><comment>68</comment><stats><homepos>68</homepos><awaypos>32</awaypos></stats><event_incident_typefk>352</event_incident_typefk><elapsed>65</elapsed><subtype>possession</subtype><sortorder>3</sortorder><awaypos>32</awaypos><homepos>68</homepos><n>352</n><type>special</type><id>6744111</id></value><value><comment>68</comment><stats><homepos>68</homepos><awaypos>32</awaypos></stats><event_incident_typefk>352</event_incident_typefk><elapsed>71</elapsed><subtype>possession</subtype><sortorder>1</sortorder><awaypos>32</awaypos><homepos>68</homepos><n>372</n><type>special</type><id>6744155</id></value><value><comment>69</comment><stats><homepos>69</homepos><awaypos>31</awaypos></stats><event_incident_typefk>352</event_incident_typefk><elapsed>76</elapsed><subtype>possession</subtype><sortorder>1</sortorder><awaypos>31</awaypos><homepos>69</homepos><n>418</n><type>special</type><id>6744199</id></value><value><comment>68</comment><stats><homepos>68</homepos><awaypos>32</awaypos></stats><event_incident_typefk>352</event_incident_typefk><elapsed>80</elapsed><subtype>possession</subtype><sortorder>0</sortorder><awaypos>32</awaypos><homepos>68</homepos><n>432</n><type>special</type><id>6744229</id></value><value><comment>68</comment><stats><homepos>68</homepos><awaypos>32</awaypos></stats><event_incident_typefk>352</event_incident_typefk><elapsed>85</elapsed><subtype>possession</subtype><sortorder>2</sortorder><awaypos>32</awaypos><homepos>68</homepos><n>459</n><type>special</type><id>6744259</id></value><value><comment>67</comment><stats><homepos>67</homepos><awaypos>33</awaypos></stats><elapsed_plus>1</elapsed_plus><event_incident_typefk>352</event_incident_typefk><elapsed>90</elapsed><subtype>possession</subtype><sortorder>4</sortorder><awaypos>33</awaypos><homepos>67</homepos><n>477</n><type>special</type><id>6744291</id></value></possession></item>